LICENSE
MANIFEST.in
README.md
requirements.txt
setup.py
mljar_scikit_plot.egg-info/PKG-INFO
mljar_scikit_plot.egg-info/SOURCES.txt
mljar_scikit_plot.egg-info/dependency_links.txt
mljar_scikit_plot.egg-info/requires.txt
mljar_scikit_plot.egg-info/top_level.txt
scikitplot/__init__.py
scikitplot/classifiers.py
scikitplot/cluster.py
scikitplot/clustering.py
scikitplot/decomposition.py
scikitplot/estimators.py
scikitplot/helpers.py
scikitplot/metrics.py
scikitplot/plotters.py